<SpawnPlacementList>
    <SpawnPlacement>
        <Position SpawnRange="0" X="1077648.0" Y="485397.4" Z="12075.0"/>
        <Walk X="1077637.0" Y="485407.2" Z="12125.0"/>
        <Direction>-0.708626228741583</Direction>
        <UseSpawnGroup SpawnCharacterKey="35628" SpawnQuantity="1"/>
        <Function>39</Function>
        <ActionIndex>0</ActionIndex>
        <DialogIndex>0</DialogIndex>
    </SpawnPlacement>
    <SpawnPlacement>
        <Position SpawnRange="0" X="1077425.0" Y="491175.0" Z="11825.0"/>
        <Walk X="1079057.0" Y="490987.0" Z="11889.6"/>
        <Direction>3.02686060827694</Direction>
        <UseSpawnGroup SpawnCharacterKey="35628" SpawnQuantity="1"/>
        <ActionIndex>0</ActionIndex>
        <DialogIndex>0</DialogIndex>
    </SpawnPlacement>
    <SpawnPlacement>
        <Position SpawnRange="0" X="1078025.0" Y="491425.0" Z="11825.0"/>
        <Walk X="1080125.0" Y="490125.0" Z="11875.0"/>
        <Direction>2.5865572493947</Direction>
        <UseSpawnGroup SpawnCharacterKey="35628" SpawnQuantity="1"/>
        <Function>64</Function>
        <ActionIndex>0</ActionIndex>
        <DialogIndex>0</DialogIndex>
    </SpawnPlacement>
    <SpawnPlacement>
        <Position SpawnRange="0" X="1080006.0" Y="490044.8" Z="11928.3"/>
        <Walk X="1079579.0" Y="490474.3" Z="11878.3"/>
        <Direction>-0.787383579087009</Direction>
        <UseSpawnGroup SpawnCharacterKey="35628" SpawnQuantity="1"/>
        <Function>200</Function>
        <ActionIndex>0</ActionIndex>
        <DialogIndex>0</DialogIndex>
    </SpawnPlacement>
    <SpawnPlacement>
        <Position SpawnRange="0" X="1079190.0" Y="495360.3" Z="11825.0"/>
        <Walk X="1079307.0" Y="495387.5" Z="11725.0"/>
        <Direction>-2.91257923730643</Direction>
        <UseSpawnGroup SpawnCharacterKey="35628" SpawnQuantity="1"/>
        <Function>199</Function>
        <ActionIndex>0</ActionIndex>
        <DialogIndex>0</DialogIndex>
    </SpawnPlacement>
    <SpawnPlacement>
        <Position SpawnRange="0" X="1078975.0" Y="497125.0" Z="11725.0"/>
        <Walk X="1076773.0" Y="498475.4" Z="11597.8"/>
        <Direction>-0.549983196117744</Direction>
        <UseSpawnGroup SpawnCharacterKey="35628" SpawnQuantity="1"/>
        <Function>71</Function>
        <ActionIndex>0</ActionIndex>
        <DialogIndex>0</DialogIndex>
    </SpawnPlacement>
    <SpawnPlacement>
        <Position SpawnRange="0" X="1080575.0" Y="498925.0" Z="11775.0"/>
        <Walk X="1081750.0" Y="497775.0" Z="11725.0"/>
        <Direction>2.36688933046498</Direction>
        <UseSpawnGroup SpawnCharacterKey="35628" SpawnQuantity="1"/>
        <ActionIndex>0</ActionIndex>
        <DialogIndex>0</DialogIndex>
    </SpawnPlacement>
    <SpawnPlacement>
        <Position SpawnRange="0" X="1086446.0" Y="493372.4" Z="11952.2"/>
        <Walk X="1087904.0" Y="491584.4" Z="11975.0"/>
        <Direction>2.25438156638398</Direction>
        <UseSpawnGroup SpawnCharacterKey="35628" SpawnQuantity="1"/>
        <Function>41</Function>
        <ActionIndex>0</ActionIndex>
        <DialogIndex>0</DialogIndex>
    </SpawnPlacement>
    <SpawnPlacement>
        <Position SpawnRange="0" X="1078975.0" Y="491375.0" Z="11825.0"/>
        <Walk X="1077752.0" Y="491023.7" Z="11875.0"/>
        <Direction>0.27921027723745</Direction>
        <UseSpawnGroup SpawnCharacterKey="35628" SpawnQuantity="1"/>
        <Function>41</Function>
        <ActionIndex>0</ActionIndex>
        <DialogIndex>0</DialogIndex>
    </SpawnPlacement>
    <SpawnPlacement>
        <Position SpawnRange="0" X="1091098.0" Y="497558.0" Z="9825.0"/>
        <Direction>-2.03723719089195</Direction>
        <UseSpawnGroup SpawnCharacterKey="35628" SpawnQuantity="1"/>
        <Function>72</Function>
        <ActionIndex>0</ActionIndex>
        <DialogIndex>0</DialogIndex>
    </SpawnPlacement>
    <SpawnPlacement>
        <Position SpawnRange="0" X="1089298.0" Y="494599.2" Z="11864.0"/>
        <Walk X="1089600.0" Y="494938.1" Z="11864.0"/>
        <Direction>-2.29782681375052</Direction>
        <UseSpawnGroup SpawnCharacterKey="35628" SpawnQuantity="1"/>
        <Function>1</Function>
        <ActionIndex>0</ActionIndex>
        <DialogIndex>0</DialogIndex>
    </SpawnPlacement>
    <SpawnPlacement>
        <Position SpawnRange="0" X="1090082.0" Y="494348.1" Z="11875.0"/>
        <Direction>-1.39540212494751</Direction>
        <UseSpawnGroup SpawnCharacterKey="35628" SpawnQuantity="1"/>
        <Function>199</Function>
        <ActionIndex>0</ActionIndex>
        <DialogIndex>0</DialogIndex>
    </SpawnPlacement>
    <SpawnPlacement>
        <Position SpawnRange="0" X="1092502.0" Y="493713.1" Z="12074.93"/>
        <Walk X="1092448.0" Y="493743.3" Z="12074.93"/>
        <Direction>-0.510188703390568</Direction>
        <UseSpawnGroup SpawnCharacterKey="35628" SpawnQuantity="1"/>
        <Function>74</Function>
        <ActionIndex>0</ActionIndex>
        <DialogIndex>0</DialogIndex>
    </SpawnPlacement>
    <SpawnPlacement>
        <Position SpawnRange="0" X="1107827.0" Y="495053.4" Z="11800.0"/>
        <Direction>1.45715579363704</Direction>
        <UseSpawnGroup SpawnCharacterKey="35628" SpawnQuantity="1"/>
        <Function>41</Function>
        <ActionIndex>0</ActionIndex>
        <DialogIndex>0</DialogIndex>
    </SpawnPlacement>
    <SpawnPlacement>
        <Position SpawnRange="0" X="1103525.0" Y="494925.0" Z="11875.0"/>
        <Direction>-1.23265378357683</Direction>
        <UseSpawnGroup SpawnCharacterKey="35628" SpawnQuantity="1"/>
        <Function>69</Function>
        <ActionIndex>0</ActionIndex>
        <DialogIndex>0</DialogIndex>
    </SpawnPlacement>
    <SpawnPlacement>
        <Position SpawnRange="0" X="1101814.0" Y="502304.5" Z="11925.0"/>
        <Direction>2.58049267372355</Direction>
        <UseSpawnGroup SpawnCharacterKey="35628" SpawnQuantity="1"/>
        <ActionIndex>0</ActionIndex>
        <DialogIndex>0</DialogIndex>
    </SpawnPlacement>
    <SpawnPlacement>
        <Position SpawnRange="0" X="1100510.0" Y="494962.0" Z="11617.1"/>
        <Direction>-0.959219360561902</Direction>
        <UseSpawnGroup SpawnCharacterKey="35628" SpawnQuantity="1"/>
        <Function>255</Function>
        <ActionIndex>0</ActionIndex>
        <DialogIndex>0</DialogIndex>
    </SpawnPlacement>
    <SpawnPlacement>
        <Position SpawnRange="0" X="1100547.0" Y="496748.0" Z="11675.0"/>
        <Direction>-2.055567582929</Direction>
        <UseSpawnGroup SpawnCharacterKey="35628" SpawnQuantity="1"/>
        <Function>54</Function>
        <ActionIndex>0</ActionIndex>
        <DialogIndex>0</DialogIndex>
    </SpawnPlacement>
    <SpawnPlacement>
        <Position SpawnRange="0" X="1093075.0" Y="500425.0" Z="11875.0"/>
        <Walk X="1094827.0" Y="499151.5" Z="11824.9"/>
        <Direction>2.51264209710154</Direction>
        <UseSpawnGroup SpawnCharacterKey="35628" SpawnQuantity="1"/>
        <Function>68</Function>
        <ActionIndex>0</ActionIndex>
        <DialogIndex>0</DialogIndex>
    </SpawnPlacement>
    <SpawnPlacement>
        <Position SpawnRange="0" X="1097193.0" Y="504618.9" Z="12075.0"/>
        <Walk X="1097303.0" Y="504549.8" Z="11975.0"/>
        <Direction>2.57745890214916</Direction>
        <UseSpawnGroup SpawnCharacterKey="35628" SpawnQuantity="1"/>
        <ActionIndex>0</ActionIndex>
        <DialogIndex>0</DialogIndex>
    </SpawnPlacement>
    <SpawnPlacement>
        <Position SpawnRange="0" X="1095010.0" Y="504849.3" Z="11925.6"/>
        <Walk X="1096179.0" Y="505046.8" Z="11925.6"/>
        <Direction>-2.97414797775122</Direction>
        <UseSpawnGroup SpawnCharacterKey="35628" SpawnQuantity="1"/>
        <ActionIndex>0</ActionIndex>
        <DialogIndex>0</DialogIndex>
    </SpawnPlacement>
    <SpawnPlacement>
        <Position SpawnRange="0" X="1094496.0" Y="506258.3" Z="11975.0"/>
        <Direction>1.89762299096121</Direction>
        <UseSpawnGroup SpawnCharacterKey="35628" SpawnQuantity="1"/>
        <ActionIndex>0</ActionIndex>
        <DialogIndex>0</DialogIndex>
    </SpawnPlacement>
    <SpawnPlacement>
        <Position SpawnRange="0" X="1094665.0" Y="507396.4" Z="12025.0"/>
        <Walk X="1094475.0" Y="508725.0" Z="12075.0"/>
        <Direction>-1.42893882774356</Direction>
        <UseSpawnGroup SpawnCharacterKey="35628" SpawnQuantity="1"/>
        <Function>4</Function>
        <ActionIndex>0</ActionIndex>
        <DialogIndex>0</DialogIndex>
    </SpawnPlacement>
    <SpawnPlacement>
        <Position SpawnRange="0" X="1095242.0" Y="502980.3" Z="11872.5"/>
        <Walk X="1093125.0" Y="502425.0" Z="11975.0"/>
        <Direction>0.256662597336388</Direction>
        <UseSpawnGroup SpawnCharacterKey="35628" SpawnQuantity="1"/>
        <Function>22</Function>
        <ActionIndex>0</ActionIndex>
        <DialogIndex>0</DialogIndex>
    </SpawnPlacement>
    <SpawnPlacement>
        <Position SpawnRange="0" X="1101772.0" Y="498119.4" Z="11690.2"/>
        <Direction>-0.575182744009072</Direction>
        <UseSpawnGroup SpawnCharacterKey="35628" SpawnQuantity="1"/>
        <ActionIndex>0</ActionIndex>
        <DialogIndex>0</DialogIndex>
    </SpawnPlacement>
    <SpawnPlacement>
        <Position SpawnRange="0" X="1104308.0" Y="497751.6" Z="11782.3"/>
        <Direction>1.07547426381103</Direction>
        <UseSpawnGroup SpawnCharacterKey="35628" SpawnQuantity="1"/>
        <Function>42</Function>
        <ActionIndex>0</ActionIndex>
        <DialogIndex>0</DialogIndex>
    </SpawnPlacement>
    <SpawnPlacement>
        <Position SpawnRange="0" X="1104854.0" Y="500674.3" Z="11721.8"/>
        <Direction>0.507279668628363</Direction>
        <UseSpawnGroup SpawnCharacterKey="35628" SpawnQuantity="1"/>
        <ActionIndex>0</ActionIndex>
        <DialogIndex>0</DialogIndex>
    </SpawnPlacement>
    <SpawnPlacement>
        <Position SpawnRange="0" X="1106309.0" Y="496391.9" Z="11825.0"/>
        <Direction>-0.0343002654840459</Direction>
        <UseSpawnGroup SpawnCharacterKey="35628" SpawnQuantity="1"/>
        <ActionIndex>0</ActionIndex>
        <DialogIndex>0</DialogIndex>
    </SpawnPlacement>
    <SpawnPlacement>
        <Position SpawnRange="0" X="1105690.0" Y="498193.3" Z="11725.0"/>
        <Walk X="1104300.0" Y="498158.5" Z="11675.0"/>
        <Direction>0.0250181688144244</Direction>
        <UseSpawnGroup SpawnCharacterKey="35628" SpawnQuantity="1"/>
        <ActionIndex>0</ActionIndex>
        <DialogIndex>0</DialogIndex>
    </SpawnPlacement>
    <SpawnPlacement>
        <Position SpawnRange="0" X="1104215.0" Y="498879.3" Z="11664.6"/>
        <Walk X="1103075.0" Y="499275.0" Z="11625.0"/>
        <Direction>-0.334161326636744</Direction>
        <UseSpawnGroup SpawnCharacterKey="35628" SpawnQuantity="1"/>
        <Function>4</Function>
        <ActionIndex>0</ActionIndex>
        <DialogIndex>0</DialogIndex>
    </SpawnPlacement>
    <SpawnPlacement>
        <Position SpawnRange="0" X="1097625.0" Y="497625.0" Z="11875.0"/>
        <Walk X="1097828.0" Y="495682.6" Z="11824.1"/>
        <Direction>1.67493132778771</Direction>
        <UseSpawnGroup SpawnCharacterKey="35628" SpawnQuantity="1"/>
        <Function>198</Function>
        <ActionIndex>0</ActionIndex>
        <DialogIndex>0</DialogIndex>
    </SpawnPlacement>
    <SpawnPlacement>
        <Position SpawnRange="0" X="1098032.0" Y="502745.3" Z="11818.6"/>
        <Direction>-1.94388512891918</Direction>
        <UseSpawnGroup SpawnCharacterKey="35628" SpawnQuantity="1"/>
        <ActionIndex>0</ActionIndex>
        <DialogIndex>0</DialogIndex>
    </SpawnPlacement>
    <SpawnPlacement>
        <Position SpawnRange="0" X="1102010.0" Y="492621.2" Z="11632.1"/>
        <Walk X="1101425.0" Y="494601.7" Z="11682.1"/>
        <Direction>-1.28376193597377</Direction>
        <UseSpawnGroup SpawnCharacterKey="35628" SpawnQuantity="1"/>
        <Function>4</Function>
        <ActionIndex>0</ActionIndex>
        <DialogIndex>0</DialogIndex>
    </SpawnPlacement>
    <SpawnPlacement>
        <Position SpawnRange="0" X="1103157.0" Y="495443.9" Z="11813.2"/>
        <Direction>0.768185415558618</Direction>
        <UseSpawnGroup SpawnCharacterKey="35628" SpawnQuantity="1"/>
        <ActionIndex>0</ActionIndex>
        <DialogIndex>0</DialogIndex>
    </SpawnPlacement>
    <SpawnPlacement>
        <Position SpawnRange="0" X="1104225.0" Y="494525.0" Z="11875.0"/>
        <Walk X="1105675.0" Y="495325.0" Z="11775.0"/>
        <Direction>-2.63757806439636</Direction>
        <UseSpawnGroup SpawnCharacterKey="35628" SpawnQuantity="1"/>
        <Function>97</Function>
        <ActionIndex>0</ActionIndex>
        <DialogIndex>0</DialogIndex>
    </SpawnPlacement>
    <SpawnPlacement>
        <Position SpawnRange="0" X="1109725.0" Y="495925.0" Z="11825.0"/>
        <Direction>0.959476730572323</Direction>
        <UseSpawnGroup SpawnCharacterKey="35628" SpawnQuantity="1"/>
        <Function>255</Function>
        <ActionIndex>0</ActionIndex>
        <DialogIndex>0</DialogIndex>
    </SpawnPlacement>
    <SpawnPlacement>
        <Position SpawnRange="0" X="1109355.0" Y="498297.5" Z="11775.0"/>
        <Direction>-1.95337201990745</Direction>
        <UseSpawnGroup SpawnCharacterKey="35628" SpawnQuantity="1"/>
        <ActionIndex>0</ActionIndex>
        <DialogIndex>0</DialogIndex>
    </SpawnPlacement>
    <SpawnPlacement>
        <Position SpawnRange="0" X="1103792.0" Y="490408.3" Z="11625.0"/>
        <Direction>1.36530918267436</Direction>
        <UseSpawnGroup SpawnCharacterKey="35628" SpawnQuantity="1"/>
        <Function>64</Function>
        <ActionIndex>0</ActionIndex>
        <DialogIndex>0</DialogIndex>
    </SpawnPlacement>
    <SpawnPlacement>
        <Position SpawnRange="0" X="1101525.0" Y="490425.0" Z="11525.0"/>
        <Walk X="1102403.0" Y="488756.5" Z="11675.0"/>
        <Direction>2.05570839669574</Direction>
        <UseSpawnGroup SpawnCharacterKey="35628" SpawnQuantity="1"/>
        <Function>72</Function>
        <ActionIndex>0</ActionIndex>
        <DialogIndex>0</DialogIndex>
    </SpawnPlacement>
    <SpawnPlacement>
        <Position SpawnRange="0" X="1101719.0" Y="489744.9" Z="11526.1"/>
        <Walk X="1102025.0" Y="491975.0" Z="11625.0"/>
        <Direction>-1.70747991640998</Direction>
        <UseSpawnGroup SpawnCharacterKey="35628" SpawnQuantity="1"/>
        <ActionIndex>0</ActionIndex>
        <DialogIndex>0</DialogIndex>
    </SpawnPlacement>
    <SpawnPlacement>
        <Position SpawnRange="0" X="1106196.0" Y="492750.8" Z="11925.0"/>
        <Direction>-3.05431494811178</Direction>
        <UseSpawnGroup SpawnCharacterKey="35628" SpawnQuantity="1"/>
        <ActionIndex>0</ActionIndex>
        <DialogIndex>0</DialogIndex>
    </SpawnPlacement>
    <SpawnPlacement>
        <Position SpawnRange="0" X="1077884.0" Y="489309.2" Z="12075.0"/>
        <Direction>1.50408960060331</Direction>
        <UseSpawnGroup SpawnCharacterKey="35632" SpawnQuantity="1"/>
        <Function>72</Function>
        <ActionIndex>0</ActionIndex>
        <DialogIndex>0</DialogIndex>
    </SpawnPlacement>
    <SpawnPlacement>
        <Position SpawnRange="0" X="1077143.0" Y="492844.5" Z="11875.0"/>
        <Walk X="1077247.0" Y="492810.1" Z="11925.0"/>
        <Direction>2.82325505738323</Direction>
        <UseSpawnGroup SpawnCharacterKey="35632" SpawnQuantity="1"/>
        <Function>69</Function>
        <ActionIndex>0</ActionIndex>
        <DialogIndex>0</DialogIndex>
    </SpawnPlacement>
    <SpawnPlacement>
        <Position SpawnRange="0" X="1076849.0" Y="496901.2" Z="11775.0"/>
        <Direction>-2.48541396570691</Direction>
        <UseSpawnGroup SpawnCharacterKey="35632" SpawnQuantity="1"/>
        <Function>41</Function>
        <ActionIndex>0</ActionIndex>
        <DialogIndex>0</DialogIndex>
    </SpawnPlacement>
    <SpawnPlacement>
        <Position SpawnRange="0" X="1079725.0" Y="495925.0" Z="11675.0"/>
        <Walk X="1079398.0" Y="497939.5" Z="11775.0"/>
        <Direction>-1.41029247992445</Direction>
        <UseSpawnGroup SpawnCharacterKey="35632" SpawnQuantity="1"/>
        <Function>255</Function>
        <ActionIndex>0</ActionIndex>
        <DialogIndex>0</DialogIndex>
    </SpawnPlacement>
    <SpawnPlacement>
        <Position SpawnRange="0" X="1081375.0" Y="498025.0" Z="11725.0"/>
        <Direction>0.533164618298265</Direction>
        <UseSpawnGroup SpawnCharacterKey="35632" SpawnQuantity="1"/>
        <ActionIndex>0</ActionIndex>
        <DialogIndex>0</DialogIndex>
    </SpawnPlacement>
    <SpawnPlacement>
        <Position SpawnRange="0" X="1097112.0" Y="502493.2" Z="11822.0"/>
        <Walk X="1098467.0" Y="504240.8" Z="11925.0"/>
        <Direction>-2.23288442257906</Direction>
        <UseSpawnGroup SpawnCharacterKey="35632" SpawnQuantity="1"/>
        <ActionIndex>0</ActionIndex>
        <DialogIndex>0</DialogIndex>
    </SpawnPlacement>
    <SpawnPlacement>
        <Position SpawnRange="0" X="1097649.0" Y="498184.8" Z="12025.0"/>
        <Walk X="1098275.0" Y="498275.0" Z="11925.0"/>
        <Direction>-2.99808246148692</Direction>
        <UseSpawnGroup SpawnCharacterKey="35632" SpawnQuantity="1"/>
        <Function>199</Function>
        <ActionIndex>0</ActionIndex>
        <DialogIndex>0</DialogIndex>
    </SpawnPlacement>
    <SpawnPlacement>
        <Position SpawnRange="0" X="1104052.0" Y="499846.8" Z="11675.0"/>
        <Direction>-0.17479970530705</Direction>
        <UseSpawnGroup SpawnCharacterKey="35632" SpawnQuantity="1"/>
        <Function>4</Function>
        <ActionIndex>0</ActionIndex>
        <DialogIndex>0</DialogIndex>
    </SpawnPlacement>
    <SpawnPlacement>
        <Position SpawnRange="0" X="1104287.0" Y="499142.2" Z="11675.0"/>
        <Direction>-1.21046245439777</Direction>
        <UseSpawnGroup SpawnCharacterKey="35632" SpawnQuantity="1"/>
        <Function>255</Function>
        <ActionIndex>0</ActionIndex>
        <DialogIndex>0</DialogIndex>
    </SpawnPlacement>
    <SpawnPlacement>
        <Position SpawnRange="0" X="1106446.0" Y="500002.7" Z="11675.0"/>
        <Direction>2.88107621810134</Direction>
        <UseSpawnGroup SpawnCharacterKey="35632" SpawnQuantity="1"/>
        <ActionIndex>0</ActionIndex>
        <DialogIndex>0</DialogIndex>
    </SpawnPlacement>
    <SpawnPlacement>
        <Position SpawnRange="0" X="1104058.0" Y="496950.5" Z="11763.2"/>
        <Walk X="1102057.0" Y="497425.6" Z="11825.0"/>
        <Direction>-0.233112547624639</Direction>
        <UseSpawnGroup SpawnCharacterKey="35632" SpawnQuantity="1"/>
        <Function>255</Function>
        <ActionIndex>0</ActionIndex>
        <DialogIndex>0</DialogIndex>
    </SpawnPlacement>
    <SpawnPlacement>
        <Position SpawnRange="0" X="1100340.0" Y="498816.6" Z="11691.8"/>
        <Walk X="1100978.0" Y="499901.6" Z="11741.8"/>
        <Direction>-2.10211080801559</Direction>
        <UseSpawnGroup SpawnCharacterKey="35632" SpawnQuantity="1"/>
        <Function>255</Function>
        <ActionIndex>0</ActionIndex>
        <DialogIndex>0</DialogIndex>
    </SpawnPlacement>
    <SpawnPlacement>
        <Position SpawnRange="0" X="1099298.0" Y="495488.6" Z="11625.0"/>
        <Walk X="1101175.0" Y="495925.0" Z="11675.0"/>
        <Direction>-2.91345041956365</Direction>
        <UseSpawnGroup SpawnCharacterKey="35632" SpawnQuantity="1"/>
        <ActionIndex>0</ActionIndex>
        <DialogIndex>0</DialogIndex>
    </SpawnPlacement>
    <SpawnPlacement>
        <Position SpawnRange="0" X="1109601.0" Y="496146.8" Z="11869.7"/>
        <Walk X="1110175.0" Y="497605.5" Z="11869.7"/>
        <Direction>-1.94501305039588</Direction>
        <UseSpawnGroup SpawnCharacterKey="35632" SpawnQuantity="1"/>
        <Function>200</Function>
        <ActionIndex>0</ActionIndex>
        <DialogIndex>0</DialogIndex>
    </SpawnPlacement>
    <SpawnPlacement>
        <Position SpawnRange="0" X="1103763.0" Y="491462.6" Z="11692.0"/>
        <Walk X="1103396.0" Y="493362.6" Z="11875.0"/>
        <Direction>-1.38033421326337</Direction>
        <UseSpawnGroup SpawnCharacterKey="35632" SpawnQuantity="1"/>
        <ActionIndex>0</ActionIndex>
        <DialogIndex>0</DialogIndex>
    </SpawnPlacement>
</SpawnPlacementList>
